algokit_subscriber/__init__.py
algokit_subscriber/block.py
algokit_subscriber/indexer_lookup.py
algokit_subscriber/subscriber.py
algokit_subscriber/subscription.py
algokit_subscriber/transform.py
algokit_subscriber/types/__init__.py
algokit_subscriber/types/arc28.py
algokit_subscriber/types/block.py
algokit_subscriber/types/event_emitter.py
algokit_subscriber/types/indexer.py
algokit_subscriber/types/subscription.py
algokit_subscriber/types/transaction.py
algokit_subscriber/utils.py
algokit_subscriber-1.0.1.dist-info/METADATA
algokit_subscriber-1.0.1.dist-info/WHEEL
algokit_subscriber-1.0.1.dist-info/RECORD
