Metadata-Version: 2.3
Name: algokit-subscriber
Version: 1.0.1
Summary: 
Author: Algorand Foundation
Requires-Python: >=3.12,<4.0
Classifier: Programming Language :: Python :: 3
Classifier: Programming Language :: Python :: 3.12
Classifier: Programming Language :: Python :: 3.13
Requires-Dist: py-algorand-sdk (>=2.9.1,<3.0.0)
